MANIFEST.in
setup.py
hug_sentry/__init__.py
hug_sentry/sentry_handler.py
hug_sentry.egg-info/PKG-INFO
hug_sentry.egg-info/SOURCES.txt
hug_sentry.egg-info/dependency_links.txt
hug_sentry.egg-info/not-zip-safe
hug_sentry.egg-info/requires.txt
hug_sentry.egg-info/top_level.txt