Metadata-Version: 1.1
Name: hug-sentry
Version: 0.0.2
Summary: Sentry Exception Handler for hug
Home-page: https://github.com/conceptsandtraining/hug_sentry
Author: Fabian Kochem
Author-email: fabian.kochem@concepts-and-training.de
License: UNKNOWN
Platform: UNKNOWN
Classifier: Development Status :: 3 - Alpha
Classifier: Intended Audience :: Developers
Classifier: License :: OSI Approved :: MIT License
Classifier: Operating System :: OS Independent
Classifier: Programming Language :: Python
Classifier: Programming Language :: Python :: 3
Classifier: Topic :: Database
Classifier: Topic :: Software Development :: Libraries
